graiax/cli/__init__.py
graiax/cli/command/__init__.py
graiax/cli/command/init.py
graiax/cli/command/inject.py
graiax/cli/prompt/__init__.py
graiax/cli/prompt/boolean.py
graiax/cli/prompt/export.py
graiax/cli/prompt/select.py
graiax/cli/prompt/text.py
graiax/cli/util.py
graiax_cli-0.11.0.dist-info/entry_points.txt
graiax_cli-0.11.0.dist-info/LICENSE
graiax_cli-0.11.0.dist-info/WHEEL
graiax_cli-0.11.0.dist-info/METADATA
graiax_cli-0.11.0.dist-info/RECORD
