Metadata-Version: 2.1
Name: graiax-cli
Version: 0.11.0
Summary: Command line tool for Graia Framework.
Home-page: https://github.com/GraiaCommunity/CLI
License: MIT
Keywords: bot,qq,graia,graiax,cli
Author: BlueGlassBlock
Author-email: blueglassblock@outlook.com
Requires-Python: >=3.8,<4.0
Classifier: Development Status :: 4 - Beta
Classifier: Framework :: Robot Framework
Classifier: Framework :: Robot Framework :: Library
Classifier: License :: OSI Approved :: MIT License
Classifier: Operating System :: OS Independent
Classifier: Programming Language :: Python :: 3
Classifier: Programming Language :: Python :: 3.10
Classifier: Programming Language :: Python :: 3.8
Classifier: Programming Language :: Python :: 3.9
Provides-Extra: fwatch
Provides-Extra: watchgod
Requires-Dist: click-completion (>=0.5.2,<0.6.0)
Requires-Dist: prompt-toolkit (>=3.0.26,<4.0.0)
Requires-Dist: pyfiglet (>=0.8.post1,<0.9)
Requires-Dist: tomlkit (>=0.9.2,<0.10.0)
Requires-Dist: typer (>=0.4.0,<0.5.0)
Requires-Dist: watchgod (>=0.7,<0.8); extra == "fwatch" or extra == "watchgod"
Project-URL: Repository, https://github.com/GraiaCommunity/CLI
